[
  {
    "concept_id": "C001",
    "name_cn": "道",
    "marker": "〖道〗",
    "category": "本体论",
    "definition": "庄子之道非老子之生成论大道，而是遍在于万物、无所不在的'通'。道在蝼蚁、在瓦甓、在屎溺——不在高远处，就在日常中。道不可言，言者非道。",
    "key_properties": ["无所不在", "不可言说", "自本自根", "无终无始"],
    "related_concepts": ["〖自然〗", "〖天〗", "〖德〗", "〖化〗"],
    "examples": [
      {"chapter": "知北游", "description": "东郭子问道，庄子答'在蝼蚁、在瓦甓、在屎溺'"}
    ]
  },
  {
    "concept_id": "C002",
    "name_cn": "逍遥",
    "marker": "〖逍遥〗",
    "category": "境界论",
    "definition": "逍遥即'无待'——不依赖任何外在条件的精神自由。大鹏待风而行非真逍遥，列子御风而行犹有所待。唯有'乘天地之正，御六气之辩，以游无穷者'才是真逍遥。",
    "key_properties": ["无待", "游于无穷", "无己无功无名"],
    "related_concepts": ["〖吾丧我〗", "〖心斋〗", "〖坐忘〗"],
    "examples": [
      {"chapter": "逍遥游", "description": "大鹏虽大犹有所待，至人无己神人无功圣人无名"}
    ]
  },
  {
    "concept_id": "C003",
    "name_cn": "齐物",
    "marker": "〖齐物〗",
    "category": "认识论",
    "definition": "齐物即'天地与我并生，万物与我为一'。破除是非、彼此、物我的分别——'彼是莫得其偶，谓之道枢'。是非之争源于成心，齐物则泯是非、和之以天倪。",
    "key_properties": ["泯是非", "道枢", "天倪", "两行"],
    "related_concepts": ["〖道〗", "〖吾丧我〗", "〖天〗"],
    "examples": [
      {"chapter": "齐物论", "description": "庄周梦蝶：不知周之梦为蝴蝶与，蝴蝶之梦为周与"},
      {"chapter": "齐物论", "description": "朝三暮四：名实未亏而喜怒为用"}
    ]
  },
  {
    "concept_id": "C004",
    "name_cn": "自然",
    "marker": "〖自然〗",
    "category": "方法论",
    "definition": "自然不是自然界，而是'自己如此'——物各其性，自然而然。庄子说的'天'不是主宰之天而是天然之天。'牛马四足是谓天，络马首穿牛鼻是谓人'——自然是本然状态，人为是对自然的破坏。",
    "key_properties": ["自己如此", "非人为", "本然状态"],
    "related_concepts": ["〖天〗", "〖无为〗", "〖道〗"],
    "examples": [
      {"chapter": "秋水", "description": "牛马四足是谓天，络马首穿牛鼻是谓人"},
      {"chapter": "应帝王", "description": "混沌开七窍而死——自然之死的寓言"}
    ]
  },
  {
    "concept_id": "C005",
    "name_cn": "无为",
    "marker": "〖无为〗",
    "category": "工夫论",
    "definition": "无为非不为，而是'顺物之性而不妄为'。庄子无为比老子更强调'逍遥'面向——不是统治术而是生存智慧。'无为其所不为，无欲其所不欲'。",
    "key_properties": ["顺其自然", "非不为", "不妄为"],
    "related_concepts": ["〖自然〗", "〖天〗", "〖逍遥〗"],
    "examples": [
      {"chapter": "天道", "description": "无为也则用天下而有余，有为也则为天下用而不足"}
    ]
  },
  {
    "concept_id": "C006",
    "name_cn": "天",
    "marker": "〖天〗",
    "category": "本体论",
    "definition": "庄子之天非儒家之天（义理之天、主宰之天），而是'天然'——万物本然如此的状态。天与人相对：天是未加人为的本来状态，人是刻意造作。庄子的理想是'入于天'而非'以人灭天'。",
    "key_properties": ["天然", "非主宰", "与人相对"],
    "related_concepts": ["〖自然〗", "〖人〗", "〖命〗"],
    "examples": [
      {"chapter": "秋水", "description": "无以人灭天，无以故灭命"}
    ]
  },
  {
    "concept_id": "C007",
    "name_cn": "化",
    "marker": "〖化〗",
    "category": "变化论",
    "definition": "化即万物的流转变化——鲲化为鹏、庄周化为蝴蝶。庄子认为万物无时不在'化'中，'万物皆化'。人不应抗拒变化，而应'与物化'、'与时俱化'。不化者乃是不变之'道'。",
    "key_properties": ["万物皆化", "与时俱化", "物化"],
    "related_concepts": ["〖道〗", "〖逍遥〗", "〖命〗"],
    "examples": [
      {"chapter": "逍遥游", "description": "鲲化而为鹏——突破形限的象征"},
      {"chapter": "齐物论", "description": "庄周梦蝶——物化的极致表达"}
    ]
  },
  {
    "concept_id": "C008",
    "name_cn": "心斋",
    "marker": "〖心斋〗",
    "category": "工夫论",
    "definition": "心斋是庄子特有的修行方法——'虚而待物'。不是关闭感官，而是让心保持空虚状态，不存成见、不预设判断。'气也者，虚而待物者也。唯道集虚。虚者，心斋也。'心斋的核心是'虚'。",
    "key_properties": ["虚", "集虚", "待物而非执物"],
    "related_concepts": ["〖坐忘〗", "〖道〗", "〖气〗"],
    "examples": [
      {"chapter": "人间世", "description": "颜回问仲尼何为心斋，仲尼答'若一志，无听之以耳而听之以心……'"}
    ]
  },
  {
    "concept_id": "C009",
    "name_cn": "坐忘",
    "marker": "〖坐忘〗",
    "category": "工夫论",
    "definition": "堕肢体，黜聪明，离形去知，同于大通——这就是坐忘。坐忘比心斋更进一步：不仅要虚其心，还要超越身体感官和知识束缚，与大道相通。心斋偏'虚'，坐忘偏'通'。",
    "key_properties": ["离形", "去知", "同于大通"],
    "related_concepts": ["〖心斋〗", "〖吾丧我〗", "〖道〗"],
    "examples": [
      {"chapter": "大宗师", "description": "颜回曰'回坐忘矣'——堕肢体黜聪明，离形去知同于大通"}
    ]
  },
  {
    "concept_id": "C010",
    "name_cn": "无用",
    "marker": "〖无用〗",
    "category": "辩证法",
    "definition": "庄子最独特的洞见之一——世人皆知有用之用，莫知无用之用。栎社树以不材得终其天年，大瓠以不适用而能浮游江湖。无用不仅不是缺陷，恰恰是保全自我、实现大用的前提。这是对儒家'有用'价值观的根本颠覆。",
    "key_properties": ["无用之用", "以无用为大用", "全生保身"],
    "related_concepts": ["〖逍遥〗", "〖自然〗", "〖天〗"],
    "examples": [
      {"chapter": "逍遥游", "description": "大瓠之种——以不适用而能浮游江湖"},
      {"chapter": "人间世", "description": "栎社树——以不材得终其天年"},
      {"chapter": "山木", "description": "材与不材之间——有用无用的辩证超越"}
    ]
  },
  {
    "concept_id": "C011",
    "name_cn": "吾丧我",
    "marker": "〖吾丧我〗",
    "category": "境界论",
    "definition": "'吾丧我'是《齐物论》开篇的境界——'我'（成心、偏见、小我）被消解后，'吾'（真我、与道相通的我）呈现。丧我不是消灭自我，而是破除'成心'——那个固执是非、分别彼此的虚假自我。",
    "key_properties": ["丧成心", "破偏见", "真我呈现"],
    "related_concepts": ["〖齐物〗", "〖坐忘〗", "〖心斋〗"],
    "examples": [
      {"chapter": "齐物论", "description": "南郭子綦隐机而坐，仰天而嘘，荅焉似丧其耦——今者吾丧我"}
    ]
  },
  {
    "concept_id": "C012",
    "name_cn": "命",
    "marker": "〖命〗",
    "category": "命论",
    "definition": "庄子的命不是儒家的天命（道德命令），而是'不可奈何者谓之命'——那些人力无法改变的事实的总和。面对命的态度是'知其不可奈何而安之若命'——接受但不消极。",
    "key_properties": ["不可奈何", "安之若命", "非道德命令"],
    "related_concepts": ["〖天〗", "〖化〗", "〖逍遥〗"],
    "examples": [
      {"chapter": "德充符", "description": "知不可奈何而安之若命，唯有德者能之"}
    ]
  },
  {
    "concept_id": "C013",
    "name_cn": "德",
    "marker": "〖德〗",
    "category": "德性论",
    "definition": "庄子之德非儒家之仁义道德，而是'得于道者谓之德'——个体从大道获得的自然本性。德充符篇的核心：残形者可全德，全形者可缺德。德不在外形，在内心的充实与道的相通。",
    "key_properties": ["得于道", "内在充实", "无关外形"],
    "related_concepts": ["〖道〗", "〖天〗", "〖自然〗"],
    "examples": [
      {"chapter": "德充符", "description": "王骀立不教坐不议，从之游者与仲尼相若——德充之人的感召力"},
      {"chapter": "人间世", "description": "且若亦知夫德之所荡而知之所为出乎哉？德荡乎名，知出乎争"}
    ]
  },
  {
    "concept_id": "C014",
    "name_cn": "气",
    "marker": "〖气〗",
    "category": "构成论",
    "definition": "庄子认为'通天下之一气'——万物由气构成，生是气之聚，死是气之散。气也是心斋工夫中的关键媒介——'气也者，虚而待物者也'，心的虚灵状态即气的状态。",
    "key_properties": ["通天下之气", "聚散为生死", "虚以待物"],
    "related_concepts": ["〖心斋〗", "〖化〗", "〖道〗"],
    "examples": [
      {"chapter": "大宗师", "description": "子祀子舆子犁子来四人相与语——'以天地为大炉，以造化为大冶'，死生一气"},
      {"chapter": "知北游", "description": "人之生，气之聚也；聚则为生，散则为死"}
    ]
  }
]
